traitlet_widgets/__init__.py
traitlet_widgets/factories.py
traitlet_widgets/factory.py
traitlet_widgets/filters.py
traitlet_widgets/traits.py
traitlet_widgets/types.py
traitlet_widgets/view.py
traitlet_widgets/widgets.py
traitlet_widgets-5.5.1.dist-info/METADATA
traitlet_widgets-5.5.1.dist-info/WHEEL
traitlet_widgets-5.5.1.dist-info/RECORD
