Metadata-Version: 2.1
Name: traitlet_widgets
Version: 5.5.1
Summary: A library which provides the ability to create widget views for traitlet `HasTraits` models, and also to observe changes in a model
Project-URL: repository, https://github.com/agoose77/traitlet_widgets
Author-email: Angus Hollands <goosey15@gmail.com>
License: MIT
Keywords: jupyter,mvc,traitlets,ui,widgets
Requires-Python: >=3.7
Requires-Dist: ipywidgets>=7.5.1
Requires-Dist: traitlets>=5.0.4
